{"sections":{"rich_text_GejnMQ":{"type":"rich-text","blocks":{"heading_BiC4jJ":{"type":"heading","settings":{"text":"<strong>Questions, comments or feedback? We're here to help.<\/strong>","heading_tag":"h1"}},"richtext_XiYpf6":{"type":"richtext","settings":{"content":"<p>Before you reach out, check out our <a href=\"https:\/\/puracy.com\/pages\/faq\" title=\"FAQs\">most frequently asked questions<\/a>. It's full of thorough answers to our most common questions.<\/p>"}},"button_jT79pe":{"type":"button","settings":{"style":"solid","text":"VIEW FAQS","url":"https:\/\/puracy.com\/pages\/faq","background":"","text_color":""}}},"block_order":["heading_BiC4jJ","richtext_XiYpf6","button_jT79pe"],"settings":{"color_scheme":"scheme-20a9c231-dfc7-499f-a228-15e253d4045a","separate_section_with_border":false,"content_width":"xs","text_position":"center","remove_vertical_spacing":false}},"contact_Nrbz8w":{"type":"contact","settings":{"color_scheme":"scheme-859769a5-9d5d-482f-99a5-29ccf953bb58","separate_section_with_border":false,"subheading":"","title":"<strong>Drop us a Line<\/strong>","content":""}},"rich_text_HFpfAX":{"type":"rich-text","blocks":{"richtext_nmJ9Lb":{"type":"richtext","settings":{"content":"<p>For the fastest response, email one of the following addresses, or fill out the form below. We'll get back to you within 24 business hours.<\/p><p>Customer Support: <a href=\"mailto:support@puracy.com\"><span style=\"text-decoration:underline\">support@puracy.com<\/span><\/a> or <strong>+1 (800) 769-5038<\/strong><\/p>"}}},"block_order":["richtext_nmJ9Lb"],"settings":{"color_scheme":"scheme-859769a5-9d5d-482f-99a5-29ccf953bb58","separate_section_with_border":false,"content_width":"xs","text_position":"center","remove_vertical_spacing":true}},"image_with_text_a86iMJ":{"type":"image-with-text","blocks":{"subheading_dKUGme":{"type":"subheading","settings":{"text":""}},"heading_a6A4zH":{"type":"heading","settings":{"text":"<strong>We're Only Happy If You're Happy<\/strong>","heading_tag":"h1"}},"richtext_UPtWNK":{"type":"richtext","settings":{"content":"<p>We're confident you'll love our products, but if you're not satisfied, we'll provide a full refund. We may ask for feedback or a return to help improve our offerings.<\/p>"}}},"block_order":["subheading_dKUGme","heading_a6A4zH","richtext_UPtWNK"],"settings":{"color_scheme":"scheme-859769a5-9d5d-482f-99a5-29ccf953bb58","separate_section_with_border":false,"image":"shopify:\/\/shop_images\/badge_44626b41-f170-45d6-a8d2-b1e4255d91c4.png","mobile_image":"shopify:\/\/shop_images\/badge_mobile_bbb82b36-be0b-418e-a7e5-8bdc6698a3c2.png","reveal_on_scroll":true,"image_position":"end","content_width":"sm","remove_vertical_spacing":true}},"main":{"type":"main-page","disabled":true,"settings":{"color_scheme":"","show_title":true,"page_width":"xs"}}},"order":["rich_text_GejnMQ","contact_Nrbz8w","rich_text_HFpfAX","image_with_text_a86iMJ","main"]}